scikit_build_core_conan/__init__.py
scikit_build_core_conan/build/__init__.py
scikit_build_core_conan/build/settings.py
scikit_build_core_conan/build/wheel.py
scikit_build_core_conan-0.9.1.dist-info/METADATA
scikit_build_core_conan-0.9.1.dist-info/WHEEL
scikit_build_core_conan-0.9.1.dist-info/licenses/LICENSE
scikit_build_core_conan-0.9.1.dist-info/RECORD
