Metadata-Version: 2.4
Name: scikit-build-core-conan
Version: 0.9.1
Summary: A conan plugin for scikit-build-core
Project-URL: Homepage, https://github.com/wu-vincent/scikit-build-core-conan
Project-URL: Issues, https://github.com/wu-vincent/scikit-build-core-conan/issues
Author-email: Vincent <magicdroidx@gmail.com>
License-File: LICENSE
Classifier: Development Status :: 3 - Alpha
Classifier: Intended Audience :: Developers
Classifier: Intended Audience :: Science/Research
Classifier: License :: OSI Approved :: MIT License
Classifier: Operating System :: OS Independent
Classifier: Programming Language :: Python
Classifier: Programming Language :: Python :: 3
Classifier: Programming Language :: Python :: 3 :: Only
Classifier: Programming Language :: Python :: 3.10
Classifier: Programming Language :: Python :: 3.11
Classifier: Programming Language :: Python :: 3.12
Classifier: Programming Language :: Python :: 3.13
Classifier: Topic :: Scientific/Engineering
Classifier: Topic :: Software Development :: Build Tools
Classifier: Typing :: Typed
Requires-Python: >=3.10
Requires-Dist: conan>=2.20.0
Requires-Dist: ruff>=0.14.14
Requires-Dist: scikit-build-core>=0.11.0
Requires-Dist: tomli; python_version < '3.11'
Provides-Extra: test
Requires-Dist: build>=0.8; extra == 'test'
Requires-Dist: cattrs>=22.2.0; extra == 'test'
Requires-Dist: pytest-subprocess>=1.5; extra == 'test'
Requires-Dist: pytest-xdist>=3.1; extra == 'test'
Requires-Dist: pytest>=7.2; extra == 'test'
Requires-Dist: setuptools; extra == 'test'
Requires-Dist: virtualenv>=20.20; extra == 'test'
Requires-Dist: wheel>=0.40; extra == 'test'
